[
    {
        "identifier": "01.0",
        "full_name": "C\u00f3digo do Banco na Compensa\u00e7\u00e3o",
        "start": "1",
        "end": "3",
        "length": "3",
        "num_decimals": "-",
        "num_or_str": "Num",
        "default": "",
        "reasonable_default": "33"
    },
    {
        "identifier": "02.0",
        "full_name": "Lote de Servi\u00e7o",
        "start": "4",
        "end": "7",
        "length": "4",
        "num_decimals": "-",
        "num_or_str": "Num",
        "default": "0",
        "reasonable_default": ""
    },
    {
        "identifier": "03.0",
        "full_name": "Tipo de Registro",
        "start": "8",
        "end": "8",
        "length": "1",
        "num_decimals": "-",
        "num_or_str": "Num",
        "default": "0",
        "reasonable_default": ""
    },
    {
        "identifier": "04.0",
        "full_name": "Uso Exclusivo FEBRABAN / CNAB",
        "start": "9",
        "end": "17",
        "length": "9",
        "num_decimals": "-",
        "num_or_str": "Alfa",
        "default": "Brancos",
        "reasonable_default": ""
    },
    {
        "identifier": "05.0",
        "full_name": "Tipo de Inscri\u00e7\u00e3o da Empresa",
        "start": "18",
        "end": "18",
        "length": "1",
        "num_decimals": "-",
        "num_or_str": "Num",
        "default": "",
        "reasonable_default": "Calculav\u00e9l"
    },
    {
        "identifier": "06.0",
        "full_name": "N\u00famero de Inscri\u00e7\u00e3o da Empresa",
        "start": "19",
        "end": "32",
        "length": "14",
        "num_decimals": "-",
        "num_or_str": "Num",
        "default": "",
        "reasonable_default": ""
    },
    {
        "identifier": "07.0",
        "full_name": "C\u00f3digo do Conv\u00eanio no Banco",
        "start": "33",
        "end": "52",
        "length": "20",
        "num_decimals": "-",
        "num_or_str": "Alfa",
        "default": "",
        "reasonable_default": ""
    },
    {
        "identifier": "08.0",
        "full_name": "Ag\u00eancia Mantenedora da Conta",
        "start": "53",
        "end": "57",
        "length": "5",
        "num_decimals": "-",
        "num_or_str": "Num",
        "default": "",
        "reasonable_default": ""
    },
    {
        "identifier": "09.0",
        "full_name": "D\u00edgito Verificador da Ag\u00eancia",
        "start": "58",
        "end": "58",
        "length": "1",
        "num_decimals": "-",
        "num_or_str": "Alfa",
        "default": "",
        "reasonable_default": ""
    },
    {
        "identifier": "10.0",
        "full_name": "N\u00famero da Conta Corrente",
        "start": "59",
        "end": "70",
        "length": "12",
        "num_decimals": "-",
        "num_or_str": "Num",
        "default": "",
        "reasonable_default": ""
    },
    {
        "identifier": "11.0",
        "full_name": "D\u00edgito Verificador da Conta",
        "start": "71",
        "end": "71",
        "length": "1",
        "num_decimals": "-",
        "num_or_str": "Alfa",
        "default": "",
        "reasonable_default": ""
    },
    {
        "identifier": "12.0",
        "full_name": "D\u00edgito Verificador da Ag/Conta",
        "start": "72",
        "end": "72",
        "length": "1",
        "num_decimals": "-",
        "num_or_str": "Alfa",
        "default": "",
        "reasonable_default": ""
    },
    {
        "identifier": "13.0",
        "full_name": "Nome da Empresa",
        "start": "73",
        "end": "102",
        "length": "30",
        "num_decimals": "-",
        "num_or_str": "Alfa",
        "default": "",
        "reasonable_default": ""
    },
    {
        "identifier": "14.0",
        "full_name": "Nome do Banco",
        "start": "103",
        "end": "132",
        "length": "30",
        "num_decimals": "-",
        "num_or_str": "Alfa",
        "default": "",
        "reasonable_default": ""
    },
    {
        "identifier": "15.0",
        "full_name": "Uso Exclusivo FEBRABAN / CNAB",
        "start": "133",
        "end": "142",
        "length": "10",
        "num_decimals": "-",
        "num_or_str": "Alfa",
        "default": "Brancos",
        "reasonable_default": ""
    },
    {
        "identifier": "16.0",
        "full_name": "C\u00f3digo Remessa / Retorno",
        "start": "143",
        "end": "143",
        "length": "1",
        "num_decimals": "-",
        "num_or_str": "Num",
        "default": "",
        "reasonable_default": ""
    },
    {
        "identifier": "17.0",
        "full_name": "Data de Gera\u00e7\u00e3o do Arquivo",
        "start": "144",
        "end": "151",
        "length": "8",
        "num_decimals": "-",
        "num_or_str": "Num",
        "default": "",
        "reasonable_default": "Calculav\u00e9l"
    },
    {
        "identifier": "18.0",
        "full_name": "Hora de Gera\u00e7\u00e3o do Arquivo",
        "start": "152",
        "end": "157",
        "length": "6",
        "num_decimals": "-",
        "num_or_str": "Num",
        "default": "",
        "reasonable_default": "Calculav\u00e9l"
    },
    {
        "identifier": "19.0",
        "full_name": "N\u00famero Seq\u00fcencial do Arquivo",
        "start": "158",
        "end": "163",
        "length": "6",
        "num_decimals": "-",
        "num_or_str": "Num",
        "default": "",
        "reasonable_default": ""
    },
    {
        "identifier": "20.0",
        "full_name": "N\u00famero da Vers\u00e3o do Layout do Arquivo",
        "start": "164",
        "end": "166",
        "length": "3",
        "num_decimals": "-",
        "num_or_str": "Num",
        "default": "30",
        "reasonable_default": ""
    },
    {
        "identifier": "21.0",
        "full_name": "Densidade de Grava\u00e7\u00e3o do Arquivo",
        "start": "167",
        "end": "171",
        "length": "5",
        "num_decimals": "-",
        "num_or_str": "Num",
        "default": "",
        "reasonable_default": "1600"
    },
    {
        "identifier": "22.0",
        "full_name": "Para Uso Reservado do Banco",
        "start": "172",
        "end": "191",
        "length": "20",
        "num_decimals": "-",
        "num_or_str": "Alfa",
        "default": "",
        "reasonable_default": "Vazio"
    },
    {
        "identifier": "23.0",
        "full_name": "Para Uso Reservado da Empresa",
        "start": "192",
        "end": "211",
        "length": "20",
        "num_decimals": "-",
        "num_or_str": "Alfa",
        "default": "",
        "reasonable_default": "Vazio"
    },
    {
        "identifier": "24.0",
        "full_name": "Uso Exclusivo FEBRABAN / CNAB",
        "start": "212",
        "end": "240",
        "length": "29",
        "num_decimals": "-",
        "num_or_str": "Alfa",
        "default": "Brancos",
        "reasonable_default": ""
    },
    {
        "identifier": "01.1",
        "full_name": "C\u00f3digo do Banco na Compensa\u00e7\u00e3o",
        "start": "1",
        "end": "3",
        "length": "3",
        "num_decimals": "-",
        "num_or_str": "Num",
        "default": "",
        "reasonable_default": "33"
    },
    {
        "identifier": "02.1",
        "full_name": "Lote de Servi\u00e7o",
        "start": "4",
        "end": "7",
        "length": "4",
        "num_decimals": "-",
        "num_or_str": "Num",
        "default": "",
        "reasonable_default": ""
    },
    {
        "identifier": "03.1",
        "full_name": "Tipo de Registro",
        "start": "8",
        "end": "8",
        "length": "1",
        "num_decimals": "-",
        "num_or_str": "Num",
        "default": "1",
        "reasonable_default": ""
    },
    {
        "identifier": "04.1",
        "full_name": "Tipo de Opera\u00e7\u00e3o",
        "start": "9",
        "end": "9",
        "length": "1",
        "num_decimals": "-",
        "num_or_str": "Alfa",
        "default": "",
        "reasonable_default": "E"
    },
    {
        "identifier": "05.1",
        "full_name": "Tipo de Servi\u00e7o",
        "start": "10",
        "end": "11",
        "length": "2",
        "num_decimals": "-",
        "num_or_str": "Num",
        "default": "1",
        "reasonable_default": ""
    },
    {
        "identifier": "06.1",
        "full_name": "Uso Exclusivo FEBRABAN/CNAB",
        "start": "12",
        "end": "13",
        "length": "2",
        "num_decimals": "-",
        "num_or_str": "Alfa",
        "default": "Brancos",
        "reasonable_default": ""
    },
    {
        "identifier": "07.1",
        "full_name": "N\u00ba da Vers\u00e3o do Layout do Lote",
        "start": "14",
        "end": "16",
        "length": "3",
        "num_decimals": "-",
        "num_or_str": "Num",
        "default": "30",
        "reasonable_default": ""
    },
    {
        "identifier": "08.1",
        "full_name": "Uso Exclusivo FEBRABAN/CNAB",
        "start": "17",
        "end": "17",
        "length": "1",
        "num_decimals": "-",
        "num_or_str": "Alfa",
        "default": "Brancos",
        "reasonable_default": ""
    },
    {
        "identifier": "09.1",
        "full_name": "Tipo de Inscri\u00e7\u00e3o da Empresa",
        "start": "18",
        "end": "18",
        "length": "1",
        "num_decimals": "-",
        "num_or_str": "Num",
        "default": "",
        "reasonable_default": "Calculav\u00e9l"
    },
    {
        "identifier": "10.1",
        "full_name": "N\u00ba de Inscri\u00e7\u00e3o da Empresa",
        "start": "19",
        "end": "33",
        "length": "15",
        "num_decimals": "-",
        "num_or_str": "Num",
        "default": "",
        "reasonable_default": ""
    },
    {
        "identifier": "11.1",
        "full_name": "C\u00f3digo do Conv\u00eanio no Banco",
        "start": "34",
        "end": "53",
        "length": "20",
        "num_decimals": "-",
        "num_or_str": "Alfa",
        "default": "",
        "reasonable_default": ""
    },
    {
        "identifier": "12.1",
        "full_name": "Ag\u00eancia Mantenedora da Conta",
        "start": "54",
        "end": "58",
        "length": "5",
        "num_decimals": "-",
        "num_or_str": "Num",
        "default": "",
        "reasonable_default": ""
    },
    {
        "identifier": "13.1",
        "full_name": "D\u00edgito Verificador da Conta",
        "start": "59",
        "end": "59",
        "length": "1",
        "num_decimals": "-",
        "num_or_str": "Alfa",
        "default": "",
        "reasonable_default": ""
    },
    {
        "identifier": "14.1",
        "full_name": "N\u00famero da Conta Corrente",
        "start": "60",
        "end": "71",
        "length": "12",
        "num_decimals": "-",
        "num_or_str": "Num",
        "default": "",
        "reasonable_default": ""
    },
    {
        "identifier": "15.1",
        "full_name": "D\u00edgito Verificador da Conta",
        "start": "72",
        "end": "72",
        "length": "1",
        "num_decimals": "-",
        "num_or_str": "Alfa",
        "default": "",
        "reasonable_default": ""
    },
    {
        "identifier": "16.1",
        "full_name": "D\u00edgito Verificador da Ag/Conta",
        "start": "73",
        "end": "73",
        "length": "1",
        "num_decimals": "-",
        "num_or_str": "Alfa",
        "default": "",
        "reasonable_default": ""
    },
    {
        "identifier": "17.1",
        "full_name": "Nome da Empresa",
        "start": "74",
        "end": "103",
        "length": "30",
        "num_decimals": "-",
        "num_or_str": "Alfa",
        "default": "",
        "reasonable_default": ""
    },
    {
        "identifier": "18.1",
        "full_name": "Mensagem 1",
        "start": "104",
        "end": "143",
        "length": "40",
        "num_decimals": "-",
        "num_or_str": "Alfa",
        "default": "",
        "reasonable_default": "Vazio"
    },
    {
        "identifier": "19.1",
        "full_name": "Mensagem 2",
        "start": "144",
        "end": "183",
        "length": "40",
        "num_decimals": "-",
        "num_or_str": "Alfa",
        "default": "",
        "reasonable_default": "Vazio"
    },
    {
        "identifier": "20.1",
        "full_name": "N\u00famero Remessa/Retorno",
        "start": "184",
        "end": "191",
        "length": "8",
        "num_decimals": "-",
        "num_or_str": "Num",
        "default": "",
        "reasonable_default": ""
    },
    {
        "identifier": "21.1",
        "full_name": "Data de Grava\u00e7\u00e3o Remessa/Retorno",
        "start": "192",
        "end": "199",
        "length": "8",
        "num_decimals": "-",
        "num_or_str": "Num",
        "default": "",
        "reasonable_default": "Calculav\u00e9l"
    },
    {
        "identifier": "22.1",
        "full_name": "Data do Cr\u00e9dito",
        "start": "200",
        "end": "207",
        "length": "8",
        "num_decimals": "-",
        "num_or_str": "Num",
        "default": "",
        "reasonable_default": "Vazio"
    },
    {
        "identifier": "23.1",
        "full_name": "Uso Exclusivo FEBRABAN/CNAB",
        "start": "208",
        "end": "240",
        "length": "33",
        "num_decimals": "-",
        "num_or_str": "Alfa",
        "default": "Brancos",
        "reasonable_default": ""
    },
    {
        "identifier": "01.3P",
        "full_name": "C\u00f3digo do Banco na Compensa\u00e7\u00e3o",
        "start": "1",
        "end": "3",
        "length": "3",
        "num_decimals": "-",
        "num_or_str": "Num",
        "default": "",
        "reasonable_default": "33"
    },
    {
        "identifier": "02.3P",
        "full_name": "Lote de Servi\u00e7o",
        "start": "4",
        "end": "7",
        "length": "4",
        "num_decimals": "-",
        "num_or_str": "Num",
        "default": "",
        "reasonable_default": "Calculav\u00e9l"
    },
    {
        "identifier": "03.3P",
        "full_name": "Tipo de Registro",
        "start": "8",
        "end": "8",
        "length": "1",
        "num_decimals": "-",
        "num_or_str": "Num",
        "default": "3",
        "reasonable_default": ""
    },
    {
        "identifier": "04.3P",
        "full_name": "N\u00ba Sequencial do Registro no Lote",
        "start": "9",
        "end": "13",
        "length": "5",
        "num_decimals": "-",
        "num_or_str": "Num",
        "default": "",
        "reasonable_default": "Calculav\u00e9l"
    },
    {
        "identifier": "05.3P",
        "full_name": "C\u00f3d. Segmento do Registro Detalhe",
        "start": "14",
        "end": "14",
        "length": "1",
        "num_decimals": "-",
        "num_or_str": "Alfa",
        "default": "P",
        "reasonable_default": ""
    },
    {
        "identifier": "06.3P",
        "full_name": "Uso Exclusivo FEBRABAN/CNAB",
        "start": "15",
        "end": "15",
        "length": "1",
        "num_decimals": "-",
        "num_or_str": "Alfa",
        "default": "Brancos",
        "reasonable_default": ""
    },
    {
        "identifier": "07.3P",
        "full_name": "C\u00f3digo de Movimento Remessa",
        "start": "16",
        "end": "17",
        "length": "2",
        "num_decimals": "-",
        "num_or_str": "Num",
        "default": "",
        "reasonable_default": ""
    },
    {
        "identifier": "08.3P",
        "full_name": "Ag\u00eancia Mantenedora da Conta",
        "start": "18",
        "end": "22",
        "length": "5",
        "num_decimals": "-",
        "num_or_str": "Num",
        "default": "",
        "reasonable_default": ""
    },
    {
        "identifier": "09.3P",
        "full_name": "D\u00edgito Verificador da Ag\u00eancia",
        "start": "23",
        "end": "23",
        "length": "1",
        "num_decimals": "-",
        "num_or_str": "Alfa",
        "default": "",
        "reasonable_default": ""
    },
    {
        "identifier": "10.3P",
        "full_name": "N\u00famero da Conta Corrente",
        "start": "24",
        "end": "35",
        "length": "12",
        "num_decimals": "-",
        "num_or_str": "Num",
        "default": "",
        "reasonable_default": ""
    },
    {
        "identifier": "11.3P",
        "full_name": "D\u00edgito Verificador da Conta",
        "start": "36",
        "end": "36",
        "length": "1",
        "num_decimals": "-",
        "num_or_str": "Alfa",
        "default": "",
        "reasonable_default": ""
    },
    {
        "identifier": "12.3P",
        "full_name": "D\u00edgito Verificador da Ag/Conta",
        "start": "37",
        "end": "37",
        "length": "1",
        "num_decimals": "-",
        "num_or_str": "Alfa",
        "default": "",
        "reasonable_default": ""
    },
    {
        "identifier": "13.3P",
        "full_name": "Identifica\u00e7\u00e3o do T\u00edtulo no Banco",
        "start": "38",
        "end": "57",
        "length": "20",
        "num_decimals": "-",
        "num_or_str": "Alfa",
        "default": "",
        "reasonable_default": ""
    },
    {
        "identifier": "14.3P",
        "full_name": "C\u00f3digo da Carteira",
        "start": "58",
        "end": "58",
        "length": "1",
        "num_decimals": "-",
        "num_or_str": "Num",
        "default": "",
        "reasonable_default": ""
    },
    {
        "identifier": "15.3P",
        "full_name": "Forma de Cadastr. do T\u00edtulo no Banco",
        "start": "59",
        "end": "59",
        "length": "1",
        "num_decimals": "-",
        "num_or_str": "Num",
        "default": "",
        "reasonable_default": ""
    },
    {
        "identifier": "16.3P",
        "full_name": "Tipo de Documento",
        "start": "60",
        "end": "60",
        "length": "1",
        "num_decimals": "-",
        "num_or_str": "Alfa",
        "default": "",
        "reasonable_default": ""
    },
    {
        "identifier": "17.3P",
        "full_name": "Identifica\u00e7\u00e3o da Emiss\u00e3o do Bloqueto",
        "start": "61",
        "end": "61",
        "length": "1",
        "num_decimals": "-",
        "num_or_str": "Num",
        "default": "",
        "reasonable_default": ""
    },
    {
        "identifier": "18.3P",
        "full_name": "Identifica\u00e7\u00e3o da Distribui\u00e7\u00e3o",
        "start": "62",
        "end": "62",
        "length": "1",
        "num_decimals": "-",
        "num_or_str": "Alfa",
        "default": "",
        "reasonable_default": ""
    },
    {
        "identifier": "19.3P",
        "full_name": "N\u00famero do Documento de Cobran\u00e7a",
        "start": "63",
        "end": "77",
        "length": "15",
        "num_decimals": "-",
        "num_or_str": "Alfa",
        "default": "",
        "reasonable_default": ""
    },
    {
        "identifier": "20.3P",
        "full_name": "Data de Vencimento do T\u00edtulo",
        "start": "78",
        "end": "85",
        "length": "8",
        "num_decimals": "-",
        "num_or_str": "Num",
        "default": "",
        "reasonable_default": ""
    },
    {
        "identifier": "21.3P",
        "full_name": "Valor Nominal do T\u00edtulo",
        "start": "86",
        "end": "100",
        "length": "13",
        "num_decimals": "2",
        "num_or_str": "Num",
        "default": "",
        "reasonable_default": ""
    },
    {
        "identifier": "22.3P",
        "full_name": "Ag\u00eancia Encarregada da Cobran\u00e7a",
        "start": "101",
        "end": "105",
        "length": "5",
        "num_decimals": "-",
        "num_or_str": "Num",
        "default": "",
        "reasonable_default": ""
    },
    {
        "identifier": "23.3P",
        "full_name": "D\u00edgito Verificador da Ag\u00eancia",
        "start": "106",
        "end": "106",
        "length": "1",
        "num_decimals": "-",
        "num_or_str": "Alfa",
        "default": "",
        "reasonable_default": ""
    },
    {
        "identifier": "24.3P",
        "full_name": "Esp\u00e9cie do T\u00edtulo",
        "start": "107",
        "end": "108",
        "length": "2",
        "num_decimals": "-",
        "num_or_str": "Num",
        "default": "",
        "reasonable_default": ""
    },
    {
        "identifier": "25.3P",
        "full_name": "Identific. De T\u00edtulo",
        "start": "109",
        "end": "109",
        "length": "1",
        "num_decimals": "-",
        "num_or_str": "Alfa",
        "default": "",
        "reasonable_default": ""
    },
    {
        "identifier": "26.3P",
        "full_name": "Data da Emiss\u00e3o do T\u00edtulo",
        "start": "110",
        "end": "117",
        "length": "8",
        "num_decimals": "-",
        "num_or_str": "Num",
        "default": "",
        "reasonable_default": ""
    },
    {
        "identifier": "27.3P",
        "full_name": "C\u00f3digo do Juros de Mora",
        "start": "118",
        "end": "118",
        "length": "1",
        "num_decimals": "-",
        "num_or_str": "Num",
        "default": "",
        "reasonable_default": ""
    },
    {
        "identifier": "28.3P",
        "full_name": "Data do Juros de Mora",
        "start": "119",
        "end": "126",
        "length": "8",
        "num_decimals": "-",
        "num_or_str": "Num",
        "default": "",
        "reasonable_default": ""
    },
    {
        "identifier": "29.3P",
        "full_name": "Juros de Mora por Dia/Taxa",
        "start": "127",
        "end": "141",
        "length": "13",
        "num_decimals": "2",
        "num_or_str": "Num",
        "default": "",
        "reasonable_default": ""
    },
    {
        "identifier": "30.3P",
        "full_name": "C\u00f3digo do Desconto 1",
        "start": "142",
        "end": "142",
        "length": "1",
        "num_decimals": "-",
        "num_or_str": "Num",
        "default": "",
        "reasonable_default": ""
    },
    {
        "identifier": "31.3P",
        "full_name": "Data do Desconto 1",
        "start": "143",
        "end": "150",
        "length": "8",
        "num_decimals": "-",
        "num_or_str": "Num",
        "default": "",
        "reasonable_default": ""
    },
    {
        "identifier": "32.3P",
        "full_name": "Valor/Percentual a ser Concedido",
        "start": "151",
        "end": "165",
        "length": "13",
        "num_decimals": "2",
        "num_or_str": "Num",
        "default": "",
        "reasonable_default": ""
    },
    {
        "identifier": "33.3P",
        "full_name": "Valor do IOF a ser Recolhido",
        "start": "166",
        "end": "180",
        "length": "13",
        "num_decimals": "2",
        "num_or_str": "Num",
        "default": "",
        "reasonable_default": ""
    },
    {
        "identifier": "34.3P",
        "full_name": "Valor do Abatimento",
        "start": "181",
        "end": "195",
        "length": "13",
        "num_decimals": "2",
        "num_or_str": "Num",
        "default": "",
        "reasonable_default": ""
    },
    {
        "identifier": "35.3P",
        "full_name": "Identifica\u00e7\u00e3o do T\u00edtulo na Empresa",
        "start": "196",
        "end": "220",
        "length": "25",
        "num_decimals": "-",
        "num_or_str": "Alfa",
        "default": "",
        "reasonable_default": ""
    },
    {
        "identifier": "36.3P",
        "full_name": "C\u00f3digo para Protesto",
        "start": "221",
        "end": "221",
        "length": "1",
        "num_decimals": "-",
        "num_or_str": "Num",
        "default": "",
        "reasonable_default": ""
    },
    {
        "identifier": "37.3P",
        "full_name": "N\u00famero de Dias para Protesto",
        "start": "222",
        "end": "223",
        "length": "2",
        "num_decimals": "-",
        "num_or_str": "Num",
        "default": "",
        "reasonable_default": ""
    },
    {
        "identifier": "38.3P",
        "full_name": "C\u00f3digo para Baixa/Devolu\u00e7\u00e3o",
        "start": "224",
        "end": "224",
        "length": "1",
        "num_decimals": "-",
        "num_or_str": "Num",
        "default": "",
        "reasonable_default": ""
    },
    {
        "identifier": "39.3P",
        "full_name": "N\u00famero de Dias para Baixa/Devolu\u00e7\u00e3o",
        "start": "225",
        "end": "227",
        "length": "3",
        "num_decimals": "-",
        "num_or_str": "Alfa",
        "default": "",
        "reasonable_default": ""
    },
    {
        "identifier": "40.3P",
        "full_name": "C\u00f3digo da Moeda",
        "start": "228",
        "end": "229",
        "length": "2",
        "num_decimals": "-",
        "num_or_str": "Num",
        "default": "9",
        "reasonable_default": ""
    },
    {
        "identifier": "41.3P",
        "full_name": "N\u00ba do Contrato da Opera\u00e7\u00e3o de Cr\u00e9d.",
        "start": "230",
        "end": "239",
        "length": "10",
        "num_decimals": "-",
        "num_or_str": "Num",
        "default": "",
        "reasonable_default": ""
    },
    {
        "identifier": "42.3P",
        "full_name": "Uso Exclusivo FEBRABAN/CNAB",
        "start": "240",
        "end": "240",
        "length": "1",
        "num_decimals": "-",
        "num_or_str": "Alfa",
        "default": "Brancos",
        "reasonable_default": ""
    },
    {
        "identifier": "01.3Q",
        "full_name": "C\u00f3digo do Banco na Compensa\u00e7\u00e3o",
        "start": "1",
        "end": "3",
        "length": "3",
        "num_decimals": "-",
        "num_or_str": "Num",
        "default": "",
        "reasonable_default": "33"
    },
    {
        "identifier": "02.3Q",
        "full_name": "Lote de Servi\u00e7o",
        "start": "4",
        "end": "7",
        "length": "4",
        "num_decimals": "-",
        "num_or_str": "Num",
        "default": "",
        "reasonable_default": ""
    },
    {
        "identifier": "03.3Q",
        "full_name": "Tipo de Registro",
        "start": "8",
        "end": "8",
        "length": "1",
        "num_decimals": "-",
        "num_or_str": "Num",
        "default": "3",
        "reasonable_default": ""
    },
    {
        "identifier": "04.3Q",
        "full_name": "N\u00ba Sequencial do Registro no Lote",
        "start": "9",
        "end": "13",
        "length": "5",
        "num_decimals": "-",
        "num_or_str": "Num",
        "default": "",
        "reasonable_default": ""
    },
    {
        "identifier": "05.3Q",
        "full_name": "C\u00f3d. Segmento do Registro Detalhe",
        "start": "14",
        "end": "14",
        "length": "1",
        "num_decimals": "-",
        "num_or_str": "Alfa",
        "default": "Q",
        "reasonable_default": ""
    },
    {
        "identifier": "06.3Q",
        "full_name": "Uso Exclusivo FEBRABAN/CNAB",
        "start": "15",
        "end": "15",
        "length": "1",
        "num_decimals": "-",
        "num_or_str": "Alfa",
        "default": "Brancos",
        "reasonable_default": ""
    },
    {
        "identifier": "07.3Q",
        "full_name": "C\u00f3digo de Movimento Remessa",
        "start": "16",
        "end": "17",
        "length": "2",
        "num_decimals": "-",
        "num_or_str": "Num",
        "default": "",
        "reasonable_default": ""
    },
    {
        "identifier": "08.3Q",
        "full_name": "Tipo de Inscri\u00e7\u00e3o",
        "start": "18",
        "end": "18",
        "length": "1",
        "num_decimals": "-",
        "num_or_str": "Num",
        "default": "",
        "reasonable_default": ""
    },
    {
        "identifier": "09.3Q",
        "full_name": "N\u00famero de Inscri\u00e7\u00e3o",
        "start": "19",
        "end": "33",
        "length": "15",
        "num_decimals": "-",
        "num_or_str": "Num",
        "default": "",
        "reasonable_default": ""
    },
    {
        "identifier": "10.3Q",
        "full_name": "Nome",
        "start": "34",
        "end": "73",
        "length": "40",
        "num_decimals": "-",
        "num_or_str": "Alfa",
        "default": "",
        "reasonable_default": ""
    },
    {
        "identifier": "11.3Q",
        "full_name": "Endere\u00e7o",
        "start": "74",
        "end": "113",
        "length": "40",
        "num_decimals": "-",
        "num_or_str": "Alfa",
        "default": "",
        "reasonable_default": ""
    },
    {
        "identifier": "12.3Q",
        "full_name": "Bairro",
        "start": "114",
        "end": "128",
        "length": "15",
        "num_decimals": "-",
        "num_or_str": "Alfa",
        "default": "",
        "reasonable_default": ""
    },
    {
        "identifier": "13.3Q",
        "full_name": "CEP",
        "start": "129",
        "end": "133",
        "length": "5",
        "num_decimals": "-",
        "num_or_str": "Num",
        "default": "",
        "reasonable_default": ""
    },
    {
        "identifier": "14.3Q",
        "full_name": "Sufixo do CEP",
        "start": "134",
        "end": "136",
        "length": "3",
        "num_decimals": "-",
        "num_or_str": "Num",
        "default": "",
        "reasonable_default": ""
    },
    {
        "identifier": "15.3Q",
        "full_name": "Cidade",
        "start": "137",
        "end": "151",
        "length": "15",
        "num_decimals": "-",
        "num_or_str": "Alfa",
        "default": "",
        "reasonable_default": ""
    },
    {
        "identifier": "16.3Q",
        "full_name": "Unidade da Federa\u00e7\u00e3o",
        "start": "152",
        "end": "153",
        "length": "2",
        "num_decimals": "-",
        "num_or_str": "Alfa",
        "default": "",
        "reasonable_default": ""
    },
    {
        "identifier": "17.3Q",
        "full_name": "Tipo de Inscri\u00e7\u00e3o",
        "start": "154",
        "end": "154",
        "length": "1",
        "num_decimals": "-",
        "num_or_str": "Num",
        "default": "",
        "reasonable_default": ""
    },
    {
        "identifier": "18.3Q",
        "full_name": "N\u00famero de Inscri\u00e7\u00e3o",
        "start": "155",
        "end": "169",
        "length": "15",
        "num_decimals": "-",
        "num_or_str": "Num",
        "default": "",
        "reasonable_default": ""
    },
    {
        "identifier": "19.3Q",
        "full_name": "Nome do Sacador/Avalista",
        "start": "170",
        "end": "209",
        "length": "40",
        "num_decimals": "-",
        "num_or_str": "Alfa",
        "default": "",
        "reasonable_default": ""
    },
    {
        "identifier": "20.3Q",
        "full_name": "C\u00f3d. Bco. Corresp. na Compensa\u00e7\u00e3o",
        "start": "210",
        "end": "212",
        "length": "3",
        "num_decimals": "-",
        "num_or_str": "Num",
        "default": "",
        "reasonable_default": ""
    },
    {
        "identifier": "21.3Q",
        "full_name": "Nosso N\u00ba no Banco Correspondente",
        "start": "213",
        "end": "232",
        "length": "20",
        "num_decimals": "-",
        "num_or_str": "Alfa",
        "default": "",
        "reasonable_default": ""
    },
    {
        "identifier": "22.3Q",
        "full_name": "Uso Exclusivo FEBRABAN/CNAB",
        "start": "233",
        "end": "240",
        "length": "8",
        "num_decimals": "-",
        "num_or_str": "Alfa",
        "default": "Brancos",
        "reasonable_default": ""
    },
    {
        "identifier": "01.3R",
        "full_name": "C\u00f3digo do Banco na Compensa\u00e7\u00e3o",
        "start": "1",
        "end": "3",
        "length": "3",
        "num_decimals": "-",
        "num_or_str": "Num",
        "default": "",
        "reasonable_default": "33"
    },
    {
        "identifier": "02.3R",
        "full_name": "Lote de Servi\u00e7o",
        "start": "4",
        "end": "7",
        "length": "4",
        "num_decimals": "-",
        "num_or_str": "Num",
        "default": "",
        "reasonable_default": ""
    },
    {
        "identifier": "03.3R",
        "full_name": "Tipo de Registro",
        "start": "8",
        "end": "8",
        "length": "1",
        "num_decimals": "-",
        "num_or_str": "Num",
        "default": "3",
        "reasonable_default": ""
    },
    {
        "identifier": "04.3R",
        "full_name": "N\u00ba Sequencial do Registro no Lote",
        "start": "9",
        "end": "13",
        "length": "5",
        "num_decimals": "-",
        "num_or_str": "Num",
        "default": "",
        "reasonable_default": ""
    },
    {
        "identifier": "05.3R",
        "full_name": "C\u00f3d. Segmento do Registro Detalhe",
        "start": "14",
        "end": "14",
        "length": "1",
        "num_decimals": "-",
        "num_or_str": "Alfa",
        "default": "R",
        "reasonable_default": ""
    },
    {
        "identifier": "06.3R",
        "full_name": "Uso Exclusivo FEBRABAN/CNAB",
        "start": "15",
        "end": "15",
        "length": "1",
        "num_decimals": "-",
        "num_or_str": "Alfa",
        "default": "Brancos",
        "reasonable_default": ""
    },
    {
        "identifier": "07.3R",
        "full_name": "C\u00f3digo de Movimento Remessa",
        "start": "16",
        "end": "17",
        "length": "2",
        "num_decimals": "-",
        "num_or_str": "Num",
        "default": "",
        "reasonable_default": ""
    },
    {
        "identifier": "08.3R",
        "full_name": "C\u00f3digo do Desconto 2",
        "start": "18",
        "end": "18",
        "length": "1",
        "num_decimals": "-",
        "num_or_str": "Num",
        "default": "",
        "reasonable_default": ""
    },
    {
        "identifier": "09.3R",
        "full_name": "Data do Desconto 2",
        "start": "19",
        "end": "26",
        "length": "8",
        "num_decimals": "-",
        "num_or_str": "Num",
        "default": "",
        "reasonable_default": ""
    },
    {
        "identifier": "10.3R",
        "full_name": "Valor/Percentual a ser Concedido",
        "start": "27",
        "end": "41",
        "length": "13",
        "num_decimals": "2/5",
        "num_or_str": "Num",
        "default": "",
        "reasonable_default": ""
    },
    {
        "identifier": "11.3R",
        "full_name": "C\u00f3digo do Desconto 3",
        "start": "42",
        "end": "42",
        "length": "1",
        "num_decimals": "-",
        "num_or_str": "Num",
        "default": "",
        "reasonable_default": ""
    },
    {
        "identifier": "12.3R",
        "full_name": "Data do Desconto 3",
        "start": "43",
        "end": "50",
        "length": "8",
        "num_decimals": "-",
        "num_or_str": "Num",
        "default": "",
        "reasonable_default": ""
    },
    {
        "identifier": "13.3R",
        "full_name": "Valor/Percentual a Ser Concedido",
        "start": "51",
        "end": "65",
        "length": "13",
        "num_decimals": "2/5",
        "num_or_str": "Num",
        "default": "",
        "reasonable_default": ""
    },
    {
        "identifier": "14.3R",
        "full_name": "C\u00f3digo da Multa",
        "start": "66",
        "end": "66",
        "length": "1",
        "num_decimals": "-",
        "num_or_str": "Alfa",
        "default": "",
        "reasonable_default": ""
    },
    {
        "identifier": "15.3R",
        "full_name": "Data da Multa",
        "start": "67",
        "end": "74",
        "length": "8",
        "num_decimals": "-",
        "num_or_str": "Num",
        "default": "",
        "reasonable_default": ""
    },
    {
        "identifier": "16.3R",
        "full_name": "Valor/Percentual a Ser Aplicado",
        "start": "75",
        "end": "89",
        "length": "13",
        "num_decimals": "2/5",
        "num_or_str": "Num",
        "default": "",
        "reasonable_default": ""
    },
    {
        "identifier": "17.3R",
        "full_name": "Informa\u00e7\u00e3o ao Pagador",
        "start": "90",
        "end": "99",
        "length": "10",
        "num_decimals": "-",
        "num_or_str": "Alfa",
        "default": "",
        "reasonable_default": ""
    },
    {
        "identifier": "18.3R",
        "full_name": "Mensagem 3",
        "start": "100",
        "end": "139",
        "length": "40",
        "num_decimals": "-",
        "num_or_str": "Alfa",
        "default": "",
        "reasonable_default": ""
    },
    {
        "identifier": "19.3R",
        "full_name": "Mensagem 4",
        "start": "140",
        "end": "179",
        "length": "40",
        "num_decimals": "-",
        "num_or_str": "Alfa",
        "default": "",
        "reasonable_default": ""
    },
    {
        "identifier": "20.3R",
        "full_name": "Uso Exclusivo FEBRABAN/CNAB",
        "start": "180",
        "end": "199",
        "length": "20",
        "num_decimals": "-",
        "num_or_str": "Alfa",
        "default": "Brancos",
        "reasonable_default": ""
    },
    {
        "identifier": "21.3R",
        "full_name": "C\u00f3d. Ocor. do Pagador",
        "start": "200",
        "end": "207",
        "length": "8",
        "num_decimals": "-",
        "num_or_str": "Num",
        "default": "",
        "reasonable_default": ""
    },
    {
        "identifier": "22.3R",
        "full_name": "C\u00f3d. do Banco na Conta do D\u00e9bito",
        "start": "208",
        "end": "210",
        "length": "3",
        "num_decimals": "-",
        "num_or_str": "Num",
        "default": "",
        "reasonable_default": ""
    },
    {
        "identifier": "23.3R",
        "full_name": "C\u00f3digo da Ag\u00eancia do D\u00e9bito",
        "start": "211",
        "end": "215",
        "length": "5",
        "num_decimals": "-",
        "num_or_str": "Num",
        "default": "",
        "reasonable_default": ""
    },
    {
        "identifier": "24.3R",
        "full_name": "D\u00edgito Verificador da Ag\u00eancia",
        "start": "216",
        "end": "216",
        "length": "1",
        "num_decimals": "-",
        "num_or_str": "Alfa",
        "default": "",
        "reasonable_default": ""
    },
    {
        "identifier": "25.3R",
        "full_name": "Conta Corrente para D\u00e9bito",
        "start": "217",
        "end": "228",
        "length": "12",
        "num_decimals": "-",
        "num_or_str": "Num",
        "default": "",
        "reasonable_default": ""
    },
    {
        "identifier": "26.3R",
        "full_name": "D\u00edgito Verificador da Conta",
        "start": "229",
        "end": "229",
        "length": "1",
        "num_decimals": "-",
        "num_or_str": "Alfa",
        "default": "",
        "reasonable_default": ""
    },
    {
        "identifier": "27.3R",
        "full_name": "D\u00edgito Verificador Ag/Conta",
        "start": "230",
        "end": "230",
        "length": "1",
        "num_decimals": "-",
        "num_or_str": "Alfa",
        "default": "",
        "reasonable_default": ""
    },
    {
        "identifier": "28.3R",
        "full_name": "Aviso para D\u00e9bito Autom\u00e1tico",
        "start": "231",
        "end": "231",
        "length": "1",
        "num_decimals": "-",
        "num_or_str": "Num",
        "default": "",
        "reasonable_default": ""
    },
    {
        "identifier": "29.3R",
        "full_name": "Uso Exclusivo FEBRABAN/CNAB",
        "start": "232",
        "end": "240",
        "length": "9",
        "num_decimals": "-",
        "num_or_str": "Alfa",
        "default": "Brancos",
        "reasonable_default": ""
    },
    {
        "identifier": "01.3S",
        "full_name": "C\u00f3digo do Banco na Compensa\u00e7\u00e3o",
        "start": "1",
        "end": "3",
        "length": "3",
        "num_decimals": "-",
        "num_or_str": "Num",
        "default": "",
        "reasonable_default": "33"
    },
    {
        "identifier": "02.3S",
        "full_name": "Lote de Servi\u00e7o",
        "start": "4",
        "end": "7",
        "length": "4",
        "num_decimals": "-",
        "num_or_str": "Num",
        "default": "",
        "reasonable_default": ""
    },
    {
        "identifier": "03.3S",
        "full_name": "Tipo de Registro",
        "start": "8",
        "end": "8",
        "length": "1",
        "num_decimals": "-",
        "num_or_str": "Num",
        "default": "3",
        "reasonable_default": ""
    },
    {
        "identifier": "04.3S",
        "full_name": "N\u00ba Sequencial do Registro no Lote",
        "start": "9",
        "end": "13",
        "length": "5",
        "num_decimals": "-",
        "num_or_str": "Num",
        "default": "",
        "reasonable_default": ""
    },
    {
        "identifier": "05.3S",
        "full_name": "C\u00f3d. Segmento do Registro Detalhe",
        "start": "14",
        "end": "14",
        "length": "1",
        "num_decimals": "-",
        "num_or_str": "Alfa",
        "default": "S",
        "reasonable_default": ""
    },
    {
        "identifier": "06.3S",
        "full_name": "Uso Exclusivo FEBRABAN/CNAB",
        "start": "15",
        "end": "15",
        "length": "1",
        "num_decimals": "-",
        "num_or_str": "Alfa",
        "default": "Brancos",
        "reasonable_default": ""
    },
    {
        "identifier": "07.3S",
        "full_name": "C\u00f3digo de Movimento Remessa",
        "start": "16",
        "end": "17",
        "length": "2",
        "num_decimals": "-",
        "num_or_str": "Num",
        "default": "",
        "reasonable_default": ""
    },
    {
        "identifier": "08.3S",
        "full_name": "Identifica\u00e7\u00e3o da Impress\u00e3o",
        "start": "18",
        "end": "18",
        "length": "1",
        "num_decimals": "-",
        "num_or_str": "Num",
        "default": "",
        "reasonable_default": ""
    },
    {
        "identifier": "09.3S",
        "full_name": "N\u00famero da Linha a ser Impressa",
        "start": "19",
        "end": "20",
        "length": "2",
        "num_decimals": "-",
        "num_or_str": "Num",
        "default": "",
        "reasonable_default": ""
    },
    {
        "identifier": "10.3S",
        "full_name": "Mensagem a ser Impressa",
        "start": "21",
        "end": "120",
        "length": "100",
        "num_decimals": "-",
        "num_or_str": "Alfa",
        "default": "",
        "reasonable_default": ""
    },
    {
        "identifier": "11.3S",
        "full_name": "Uso Exclusivo FEBRABAN/CNAB",
        "start": "121",
        "end": "160",
        "length": "40",
        "num_decimals": "-",
        "num_or_str": "Alfa",
        "default": "Brancos",
        "reasonable_default": ""
    },
    {
        "identifier": "12.3S",
        "full_name": "Tipo do Caracter a ser Impresso",
        "start": "161",
        "end": "162",
        "length": "2",
        "num_decimals": "-",
        "num_or_str": "Num",
        "default": "",
        "reasonable_default": ""
    },
    {
        "identifier": "13.3S",
        "full_name": "Uso Exclusivo FEBRABAN/CNAB",
        "start": "163",
        "end": "240",
        "length": "78",
        "num_decimals": "-",
        "num_or_str": "Alfa",
        "default": "Brancos",
        "reasonable_default": ""
    },
    {
        "identifier": "01.3T",
        "full_name": "C\u00f3digo do Banco na Compensa\u00e7\u00e3o",
        "start": "1",
        "end": "3",
        "length": "3",
        "num_decimals": "-",
        "num_or_str": "Num",
        "default": "",
        "reasonable_default": "33"
    },
    {
        "identifier": "02.3T",
        "full_name": "Lote de Servi\u00e7o",
        "start": "4",
        "end": "7",
        "length": "4",
        "num_decimals": "-",
        "num_or_str": "Num",
        "default": "",
        "reasonable_default": ""
    },
    {
        "identifier": "03.3T",
        "full_name": "Tipo de Registro",
        "start": "8",
        "end": "8",
        "length": "1",
        "num_decimals": "-",
        "num_or_str": "Num",
        "default": "3",
        "reasonable_default": ""
    },
    {
        "identifier": "04.3T",
        "full_name": "N\u00famero Sequencial Registro no Lote",
        "start": "9",
        "end": "13",
        "length": "5",
        "num_decimals": "-",
        "num_or_str": "Num",
        "default": "",
        "reasonable_default": ""
    },
    {
        "identifier": "05.3T",
        "full_name": "C\u00f3digo Segmento do Registro Detalhe",
        "start": "14",
        "end": "14",
        "length": "1",
        "num_decimals": "-",
        "num_or_str": "Alfa",
        "default": "T",
        "reasonable_default": ""
    },
    {
        "identifier": "06.3T",
        "full_name": "Uso Exclusivo FEBRABAN/CNAB",
        "start": "15",
        "end": "15",
        "length": "1",
        "num_decimals": "-",
        "num_or_str": "Alfa",
        "default": "Brancos",
        "reasonable_default": ""
    },
    {
        "identifier": "07.3T",
        "full_name": "C\u00f3digo de Movimento Retorno",
        "start": "16",
        "end": "17",
        "length": "2",
        "num_decimals": "-",
        "num_or_str": "Num",
        "default": "",
        "reasonable_default": ""
    },
    {
        "identifier": "08.3T",
        "full_name": "Ag\u00eancia Mantenedora da Conta",
        "start": "18",
        "end": "22",
        "length": "5",
        "num_decimals": "-",
        "num_or_str": "Num",
        "default": "",
        "reasonable_default": ""
    },
    {
        "identifier": "09.3T",
        "full_name": "D\u00edgito Verificador da Ag\u00eancia",
        "start": "23",
        "end": "23",
        "length": "1",
        "num_decimals": "-",
        "num_or_str": "Num",
        "default": "",
        "reasonable_default": ""
    },
    {
        "identifier": "10.3T",
        "full_name": "N\u00famero da Conta Corrente",
        "start": "24",
        "end": "35",
        "length": "12",
        "num_decimals": "-",
        "num_or_str": "Num",
        "default": "",
        "reasonable_default": ""
    },
    {
        "identifier": "11.3T",
        "full_name": "D\u00edgito Verificador da Conta",
        "start": "36",
        "end": "36",
        "length": "1",
        "num_decimals": "-",
        "num_or_str": "Num",
        "default": "",
        "reasonable_default": ""
    },
    {
        "identifier": "12.3T",
        "full_name": "D\u00edgito Verificador da Ag/Conta",
        "start": "37",
        "end": "37",
        "length": "1",
        "num_decimals": "-",
        "num_or_str": "Num",
        "default": "",
        "reasonable_default": ""
    },
    {
        "identifier": "13.3T",
        "full_name": "Identifica\u00e7\u00e3o do T\u00edtulo",
        "start": "38",
        "end": "57",
        "length": "20",
        "num_decimals": "-",
        "num_or_str": "Num",
        "default": "",
        "reasonable_default": ""
    },
    {
        "identifier": "14.3T",
        "full_name": "C\u00f3digo da Carteira",
        "start": "58",
        "end": "58",
        "length": "1",
        "num_decimals": "-",
        "num_or_str": "Num",
        "default": "",
        "reasonable_default": ""
    },
    {
        "identifier": "15.3T",
        "full_name": "N\u00famero do Documento de Cobran\u00e7a",
        "start": "59",
        "end": "73",
        "length": "15",
        "num_decimals": "-",
        "num_or_str": "Alfa",
        "default": "",
        "reasonable_default": ""
    },
    {
        "identifier": "16.3T",
        "full_name": "Data do Vencimento do T\u00edtulo",
        "start": "74",
        "end": "81",
        "length": "8",
        "num_decimals": "-",
        "num_or_str": "Num",
        "default": "",
        "reasonable_default": ""
    },
    {
        "identifier": "17.3T",
        "full_name": "Valor Nominal do T\u00edtulo",
        "start": "82",
        "end": "96",
        "length": "13",
        "num_decimals": "2",
        "num_or_str": "Num",
        "default": "",
        "reasonable_default": ""
    },
    {
        "identifier": "18.3T",
        "full_name": "N\u00famero do Banco",
        "start": "97",
        "end": "99",
        "length": "3",
        "num_decimals": "-",
        "num_or_str": "Num",
        "default": "",
        "reasonable_default": ""
    },
    {
        "identifier": "19.3T",
        "full_name": "Ag\u00eancia Cobradora/Recebedora",
        "start": "100",
        "end": "104",
        "length": "5",
        "num_decimals": "-",
        "num_or_str": "Num",
        "default": "",
        "reasonable_default": ""
    },
    {
        "identifier": "20.3T",
        "full_name": "D\u00edgito Verificador da Ag\u00eancia",
        "start": "105",
        "end": "105",
        "length": "1",
        "num_decimals": "-",
        "num_or_str": "Num",
        "default": "",
        "reasonable_default": ""
    },
    {
        "identifier": "21.3T",
        "full_name": "Identifica\u00e7\u00e3o do T\u00edtulo na Empresa",
        "start": "106",
        "end": "130",
        "length": "25",
        "num_decimals": "-",
        "num_or_str": "Alfa",
        "default": "",
        "reasonable_default": ""
    },
    {
        "identifier": "22.3T",
        "full_name": "C\u00f3digo da Moeda",
        "start": "131",
        "end": "132",
        "length": "2",
        "num_decimals": "-",
        "num_or_str": "Num",
        "default": "",
        "reasonable_default": ""
    },
    {
        "identifier": "23.3T",
        "full_name": "Tipo de Inscri\u00e7\u00e3o",
        "start": "133",
        "end": "133",
        "length": "1",
        "num_decimals": "-",
        "num_or_str": "Num",
        "default": "",
        "reasonable_default": ""
    },
    {
        "identifier": "24.3T",
        "full_name": "N\u00famero de Inscri\u00e7\u00e3o",
        "start": "134",
        "end": "148",
        "length": "15",
        "num_decimals": "-",
        "num_or_str": "Num",
        "default": "",
        "reasonable_default": ""
    },
    {
        "identifier": "25.3T",
        "full_name": "Nome",
        "start": "149",
        "end": "188",
        "length": "40",
        "num_decimals": "-",
        "num_or_str": "Alfa",
        "default": "",
        "reasonable_default": ""
    },
    {
        "identifier": "26.3T",
        "full_name": "N\u00ba do Contr. da Opera\u00e7\u00e3o de Cr\u00e9dito",
        "start": "189",
        "end": "198",
        "length": "10",
        "num_decimals": "-",
        "num_or_str": "Num",
        "default": "",
        "reasonable_default": ""
    },
    {
        "identifier": "27.3T",
        "full_name": "Valor da Tarifa / Custas",
        "start": "199",
        "end": "213",
        "length": "13",
        "num_decimals": "2",
        "num_or_str": "Num",
        "default": "",
        "reasonable_default": ""
    },
    {
        "identifier": "28.3T",
        "full_name": "Identifica\u00e7\u00e3o para Rejei\u00e7\u00f5es, Tarifas, Custas, Liquida\u00e7\u00e3o e Baixas",
        "start": "214",
        "end": "223",
        "length": "10",
        "num_decimals": "-",
        "num_or_str": "Num",
        "default": "",
        "reasonable_default": ""
    },
    {
        "identifier": "29.3T",
        "full_name": "Uso Exclusivo FEBRABAN/CNAB",
        "start": "224",
        "end": "240",
        "length": "17",
        "num_decimals": "-",
        "num_or_str": "Alfa",
        "default": "Brancos",
        "reasonable_default": ""
    },
    {
        "identifier": "01.3U",
        "full_name": "C\u00f3digo do Banco na Compensa\u00e7\u00e3o",
        "start": "1",
        "end": "3",
        "length": "3",
        "num_decimals": "-",
        "num_or_str": "Num",
        "default": "",
        "reasonable_default": "33"
    },
    {
        "identifier": "02.3U",
        "full_name": "Lote de Servi\u00e7o",
        "start": "4",
        "end": "7",
        "length": "4",
        "num_decimals": "-",
        "num_or_str": "Num",
        "default": "",
        "reasonable_default": ""
    },
    {
        "identifier": "03.3U",
        "full_name": "Tipo de Registro",
        "start": "8",
        "end": "8",
        "length": "1",
        "num_decimals": "-",
        "num_or_str": "Num",
        "default": "3",
        "reasonable_default": ""
    },
    {
        "identifier": "04.3U",
        "full_name": "N\u00ba Sequencial do Registro no Lote",
        "start": "9",
        "end": "13",
        "length": "5",
        "num_decimals": "-",
        "num_or_str": "Num",
        "default": "",
        "reasonable_default": ""
    },
    {
        "identifier": "05.3U",
        "full_name": "C\u00f3d. Segmento do Registro Detalhe",
        "start": "14",
        "end": "14",
        "length": "1",
        "num_decimals": "-",
        "num_or_str": "Alfa",
        "default": "U",
        "reasonable_default": ""
    },
    {
        "identifier": "06.3U",
        "full_name": "Uso Exclusivo FEBRABAN/CNAB",
        "start": "15",
        "end": "15",
        "length": "1",
        "num_decimals": "-",
        "num_or_str": "Alfa",
        "default": "Brancos",
        "reasonable_default": ""
    },
    {
        "identifier": "07.3U",
        "full_name": "C\u00f3digo de Movimento Retorno",
        "start": "16",
        "end": "17",
        "length": "2",
        "num_decimals": "-",
        "num_or_str": "Num",
        "default": "",
        "reasonable_default": ""
    },
    {
        "identifier": "08.3U",
        "full_name": "Juros / Multa / Encargos",
        "start": "18",
        "end": "32",
        "length": "13",
        "num_decimals": "2",
        "num_or_str": "Num",
        "default": "",
        "reasonable_default": ""
    },
    {
        "identifier": "09.3U",
        "full_name": "Valor do Desconto Concedido",
        "start": "33",
        "end": "47",
        "length": "13",
        "num_decimals": "2",
        "num_or_str": "Num",
        "default": "",
        "reasonable_default": ""
    },
    {
        "identifier": "10.3U",
        "full_name": "Valor do Abat. Concedido/Cancel.",
        "start": "48",
        "end": "62",
        "length": "13",
        "num_decimals": "2",
        "num_or_str": "Num",
        "default": "",
        "reasonable_default": ""
    },
    {
        "identifier": "11.3U",
        "full_name": "Valor do IOF Recolhido",
        "start": "63",
        "end": "77",
        "length": "13",
        "num_decimals": "2",
        "num_or_str": "Num",
        "default": "",
        "reasonable_default": ""
    },
    {
        "identifier": "12.3U",
        "full_name": "Valor Pago pelo Pagador",
        "start": "78",
        "end": "92",
        "length": "13",
        "num_decimals": "2",
        "num_or_str": "Num",
        "default": "",
        "reasonable_default": ""
    },
    {
        "identifier": "13.3U",
        "full_name": "Valor L\u00edquido a ser Creditado",
        "start": "93",
        "end": "107",
        "length": "13",
        "num_decimals": "2",
        "num_or_str": "Num",
        "default": "",
        "reasonable_default": ""
    },
    {
        "identifier": "14.3U",
        "full_name": "Valor de Outras Despesas",
        "start": "108",
        "end": "122",
        "length": "13",
        "num_decimals": "2",
        "num_or_str": "Num",
        "default": "",
        "reasonable_default": ""
    },
    {
        "identifier": "15.3U",
        "full_name": "Valor de Outros Cr\u00e9ditos",
        "start": "123",
        "end": "137",
        "length": "13",
        "num_decimals": "2",
        "num_or_str": "Num",
        "default": "",
        "reasonable_default": ""
    },
    {
        "identifier": "16.3U",
        "full_name": "Data da Ocorr\u00eancia",
        "start": "138",
        "end": "145",
        "length": "8",
        "num_decimals": "-",
        "num_or_str": "Num",
        "default": "",
        "reasonable_default": ""
    },
    {
        "identifier": "17.3U",
        "full_name": "Data da Efetiva\u00e7\u00e3o do Cr\u00e9dito",
        "start": "146",
        "end": "153",
        "length": "8",
        "num_decimals": "-",
        "num_or_str": "Num",
        "default": "",
        "reasonable_default": ""
    },
    {
        "identifier": "18.3U",
        "full_name": "C\u00f3digo da Ocorr\u00eancia",
        "start": "154",
        "end": "157",
        "length": "4",
        "num_decimals": "-",
        "num_or_str": "Alfa",
        "default": "",
        "reasonable_default": ""
    },
    {
        "identifier": "19.3U",
        "full_name": "Data da Ocorr\u00eancia",
        "start": "158",
        "end": "165",
        "length": "8",
        "num_decimals": "-",
        "num_or_str": "Alfa",
        "default": "",
        "reasonable_default": ""
    },
    {
        "identifier": "20.3U",
        "full_name": "Valor da Ocorr\u00eancia",
        "start": "166",
        "end": "180",
        "length": "13",
        "num_decimals": "2",
        "num_or_str": "Num",
        "default": "",
        "reasonable_default": ""
    },
    {
        "identifier": "21.3U",
        "full_name": "Complem. da Ocorr\u00eancia",
        "start": "181",
        "end": "210",
        "length": "30",
        "num_decimals": "-",
        "num_or_str": "Alfa",
        "default": "",
        "reasonable_default": ""
    },
    {
        "identifier": "22.3U",
        "full_name": "C\u00f3d. Banco Correspondente Compens.",
        "start": "211",
        "end": "213",
        "length": "3",
        "num_decimals": "-",
        "num_or_str": "Num",
        "default": "",
        "reasonable_default": ""
    },
    {
        "identifier": "23.3U",
        "full_name": "Nosso N\u00ba Banco Correspondente",
        "start": "214",
        "end": "233",
        "length": "20",
        "num_decimals": "-",
        "num_or_str": "Num",
        "default": "",
        "reasonable_default": ""
    },
    {
        "identifier": "24.3U",
        "full_name": "Uso Exclusivo FEBRABAN/CNAB",
        "start": "234",
        "end": "240",
        "length": "7",
        "num_decimals": "-",
        "num_or_str": "Alfa",
        "default": "Brancos",
        "reasonable_default": ""
    },
    {
        "identifier": "01.5",
        "full_name": "C\u00f3digo do Banco na Compensa\u00e7\u00e3o",
        "start": "1",
        "end": "3",
        "length": "3",
        "num_decimals": "-",
        "num_or_str": "Num",
        "default": "",
        "reasonable_default": "33"
    },
    {
        "identifier": "02.5",
        "full_name": "Lote de Servi\u00e7o",
        "start": "4",
        "end": "7",
        "length": "4",
        "num_decimals": "-",
        "num_or_str": "Num",
        "default": "",
        "reasonable_default": ""
    },
    {
        "identifier": "03.5",
        "full_name": "Tipo de Registro",
        "start": "8",
        "end": "8",
        "length": "1",
        "num_decimals": "-",
        "num_or_str": "Num",
        "default": "5",
        "reasonable_default": ""
    },
    {
        "identifier": "04.5",
        "full_name": "Uso Exclusivo FEBRABAN/CNAB",
        "start": "9",
        "end": "17",
        "length": "9",
        "num_decimals": "-",
        "num_or_str": "Alfa",
        "default": "Brancos",
        "reasonable_default": ""
    },
    {
        "identifier": "05.5",
        "full_name": "Quantidade de Registros no Lote",
        "start": "18",
        "end": "23",
        "length": "6",
        "num_decimals": "-",
        "num_or_str": "Num",
        "default": "",
        "reasonable_default": ""
    },
    {
        "identifier": "06.5",
        "full_name": "Quantidade de T\u00edtulos em Cobran\u00e7a",
        "start": "24",
        "end": "29",
        "length": "6",
        "num_decimals": "-",
        "num_or_str": "Num",
        "default": "",
        "reasonable_default": ""
    },
    {
        "identifier": "07.5",
        "full_name": "Valor Total dosT\u00edtulos em Carteiras",
        "start": "30",
        "end": "46",
        "length": "15",
        "num_decimals": "2",
        "num_or_str": "Num",
        "default": "",
        "reasonable_default": ""
    },
    {
        "identifier": "08.5",
        "full_name": "Quantidade de T\u00edtulos em Cobran\u00e7a",
        "start": "47",
        "end": "52",
        "length": "6",
        "num_decimals": "-",
        "num_or_str": "Num",
        "default": "",
        "reasonable_default": ""
    },
    {
        "identifier": "09.5",
        "full_name": "Valor Total dosT\u00edtulos em Carteiras",
        "start": "53",
        "end": "69",
        "length": "15",
        "num_decimals": "2",
        "num_or_str": "Num",
        "default": "",
        "reasonable_default": ""
    },
    {
        "identifier": "10.5",
        "full_name": "Quantidade de T\u00edtulos em Cobran\u00e7a",
        "start": "70",
        "end": "75",
        "length": "6",
        "num_decimals": "-",
        "num_or_str": "Num",
        "default": "",
        "reasonable_default": ""
    },
    {
        "identifier": "11.5",
        "full_name": "Quantidade de T\u00edtulos em Carteiras",
        "start": "76",
        "end": "92",
        "length": "15",
        "num_decimals": "2",
        "num_or_str": "Num",
        "default": "",
        "reasonable_default": ""
    },
    {
        "identifier": "12.5",
        "full_name": "Quantidade de T\u00edtulos em Cobran\u00e7a",
        "start": "93",
        "end": "98",
        "length": "6",
        "num_decimals": "-",
        "num_or_str": "Num",
        "default": "",
        "reasonable_default": ""
    },
    {
        "identifier": "13.5",
        "full_name": "Valor Total dosT\u00edtulos em Carteiras",
        "start": "99",
        "end": "115",
        "length": "15",
        "num_decimals": "2",
        "num_or_str": "Num",
        "default": "",
        "reasonable_default": ""
    },
    {
        "identifier": "14.5",
        "full_name": "N\u00famero do Aviso de Lan\u00e7amento",
        "start": "116",
        "end": "123",
        "length": "8",
        "num_decimals": "-",
        "num_or_str": "Alfa",
        "default": "",
        "reasonable_default": ""
    },
    {
        "identifier": "15.5",
        "full_name": "Uso Exclusivo FEBRABAN/CNAB",
        "start": "124",
        "end": "240",
        "length": "117",
        "num_decimals": "-",
        "num_or_str": "Alfa",
        "default": "Brancos",
        "reasonable_default": ""
    },
    {
        "identifier": "01.9",
        "full_name": "C\u00f3digo do Banco na Compensa\u00e7\u00e3o",
        "start": "1",
        "end": "3",
        "length": "3",
        "num_decimals": "-",
        "num_or_str": "Num",
        "default": "",
        "reasonable_default": "33"
    },
    {
        "identifier": "02.9",
        "full_name": "Lote de Servi\u00e7o",
        "start": "4",
        "end": "7",
        "length": "4",
        "num_decimals": "-",
        "num_or_str": "Num",
        "default": "9999",
        "reasonable_default": ""
    },
    {
        "identifier": "03.9",
        "full_name": "Tipo de Registro",
        "start": "8",
        "end": "8",
        "length": "1",
        "num_decimals": "-",
        "num_or_str": "Num",
        "default": "9",
        "reasonable_default": ""
    },
    {
        "identifier": "04.9",
        "full_name": "Uso Exclusivo FEBRABAN/CNAB",
        "start": "9",
        "end": "17",
        "length": "9",
        "num_decimals": "-",
        "num_or_str": "Alfa",
        "default": "Brancos",
        "reasonable_default": ""
    },
    {
        "identifier": "05.9",
        "full_name": "Quantidade de Lotes do Arquivo",
        "start": "18",
        "end": "23",
        "length": "6",
        "num_decimals": "-",
        "num_or_str": "Num",
        "default": "",
        "reasonable_default": "Calculav\u00e9l"
    },
    {
        "identifier": "06.9",
        "full_name": "Quantidade de Registros do Arquivo",
        "start": "24",
        "end": "29",
        "length": "6",
        "num_decimals": "-",
        "num_or_str": "Num",
        "default": "",
        "reasonable_default": "Calculav\u00e9l"
    },
    {
        "identifier": "07.9",
        "full_name": "Qtde de Contas p/ Conc. (Lotes)",
        "start": "30",
        "end": "35",
        "length": "6",
        "num_decimals": "-",
        "num_or_str": "Num",
        "default": "",
        "reasonable_default": "Calculav\u00e9l"
    },
    {
        "identifier": "08.9",
        "full_name": "Uso Exclusivo FEBRABAN/CNAB",
        "start": "36",
        "end": "240",
        "length": "205",
        "num_decimals": "-",
        "num_or_str": "Alfa",
        "default": "Brancos",
        "reasonable_default": ""
    }
]